alcazar/__init__.py
alcazar/api.py
alcazar/constants.py
alcazar/error_handlers.py
alcazar/exceptions.py
alcazar/middleware.py
alcazar/requests.py
alcazar/responses.py
alcazar/route.py
alcazar/templates.py
alcazar/utils/__init__.py
alcazar/utils/static.py
alcazar/utils/tests.py
alcazar/utils/wsgi.py
alcazar_web_framework-0.0.2.dist-info/METADATA
alcazar_web_framework-0.0.2.dist-info/WHEEL
alcazar_web_framework-0.0.2.dist-info/top_level.txt
alcazar_web_framework-0.0.2.dist-info/RECORD
