Metadata-Version: 2.1
Name: alcazar-web-framework
Version: 0.0.2
Summary: Python Web Framework built for learning purposes.
Home-page: https://github.com/rahmonov/alcazar
Author: Jahongir Rahmonov
Author-email: jrahmonov2@gmail.com   
License: MIT
Platform: UNKNOWN
Classifier: License :: OSI Approved :: MIT License
Classifier: Programming Language :: Python
Classifier: Programming Language :: Python :: 3
Classifier: Programming Language :: Python :: 3.6
Classifier: Programming Language :: Python :: Implementation :: CPython
Classifier: Programming Language :: Python :: Implementation :: PyPy
Requires-Python: >=3.6.0
Requires-Dist: Jinja2 (==2.10)
Requires-Dist: requests-wsgi-adapter (==0.4.0)
Requires-Dist: parse (==1.11.1)
Requires-Dist: requests (==2.21.0)
Requires-Dist: WebOb (==1.8.5)
Requires-Dist: whitenoise (==4.1.2)
